eetc_algo_trading/__init__.py
examples/__init__.py
examples/simple.py
tests/__init__.py
eetc_algo_trading_lib-0.2.1.dist-info/LICENSE
eetc_algo_trading_lib-0.2.1.dist-info/METADATA
eetc_algo_trading_lib-0.2.1.dist-info/WHEEL
eetc_algo_trading_lib-0.2.1.dist-info/top_level.txt
eetc_algo_trading_lib-0.2.1.dist-info/RECORD
