Metadata-Version: 2.1
Name: eetc-algo-trading-lib
Version: 0.2.1
Summary: Algorithmic Trading Library by East Empire Trading Company.
Home-page: https://github.com/delicmakaveli/eetc-trading-lib-python
Author: Stefan Delic
Author-email: eastempiretradingcompany2019@gmail.com
License: GPLv2
Platform: UNKNOWN
Classifier: Programming Language :: Python :: 3
Classifier: Operating System :: OS Independent
